CHANGELOG
COPYING
INSTALL
MANIFEST.in
README.rst
TODO
setup.py
bin/crawlidator
crawlidator/__init__.py
crawlidator/crawlidator.py
crawlidator.egg-info/PKG-INFO
crawlidator.egg-info/SOURCES.txt
crawlidator.egg-info/dependency_links.txt
crawlidator.egg-info/not-zip-safe
crawlidator.egg-info/requires.txt
crawlidator.egg-info/top_level.txt
crawlidator/dtd/xhtml-lat1.ent
crawlidator/dtd/xhtml-special.ent
crawlidator/dtd/xhtml-symbol.ent
crawlidator/dtd/xhtml1-strict.dtd
tests/__init__.py
tests/test.py
tests/expect/test.py
tests/expect/test_get_urls_from_sitemap.1
tests/expect/test_get_urls_from_sitemap.2
tests/expect/test_get_urls_from_sitemap.3
tests/fixtures/aboutCWI.html
tests/fixtures/index.html
tests/fixtures/sitemap.xml