Metadata-Version: 1.0
Name: crawlidator
Version: 0.2
Summary: A validator that crawls your sitemap.xml
Home-page: https://bitbucket.org/charstring/crawlidator
Author: Chris Wesseling
Author-email: chris.wesseling@cwi.nl
License: BSD
Keywords: validation sitemap.xml
Platform: UNKNOWN
Classifier: Development Status :: 4 - Beta
Classifier: License :: OSI Approved :: BSD License
Classifier: Environment :: Console
Classifier: Operating System :: OS Independent
Classifier: Programming Language :: Python
Classifier: Topic :: Internet :: WWW/HTTP :: Site Management :: Link Checking
Classifier: Topic :: Utilities
